README.md
setup.py
pulumi_aviatrix/__init__.py
pulumi_aviatrix/_inputs.py
pulumi_aviatrix/_utilities.py
pulumi_aviatrix/aviatrix_account.py
pulumi_aviatrix/aviatrix_account_user.py
pulumi_aviatrix/aviatrix_app_domain.py
pulumi_aviatrix/aviatrix_arm_peer.py
pulumi_aviatrix/aviatrix_aws_guard_duty.py
pulumi_aviatrix/aviatrix_aws_peer.py
pulumi_aviatrix/aviatrix_aws_tgw.py
pulumi_aviatrix/aviatrix_aws_tgw_connect.py
pulumi_aviatrix/aviatrix_aws_tgw_connect_peer.py
pulumi_aviatrix/aviatrix_aws_tgw_directconnect.py
pulumi_aviatrix/aviatrix_aws_tgw_intra_domain_inspection.py
pulumi_aviatrix/aviatrix_aws_tgw_network_domain.py
pulumi_aviatrix/aviatrix_aws_tgw_peering.py
pulumi_aviatrix/aviatrix_aws_tgw_peering_domain_conn.py
pulumi_aviatrix/aviatrix_aws_tgw_security_domain.py
pulumi_aviatrix/aviatrix_aws_tgw_security_domain_conn.py
pulumi_aviatrix/aviatrix_aws_tgw_transit_gateway_attachment.py
pulumi_aviatrix/aviatrix_aws_tgw_vpc_attachment.py
pulumi_aviatrix/aviatrix_aws_tgw_vpn_conn.py
pulumi_aviatrix/aviatrix_azure_peer.py
pulumi_aviatrix/aviatrix_azure_spoke_native_peering.py
pulumi_aviatrix/aviatrix_azure_vng_conn.py
pulumi_aviatrix/aviatrix_cloudn_registration.py
pulumi_aviatrix/aviatrix_cloudn_transit_gateway_attachment.py
pulumi_aviatrix/aviatrix_cloudwatch_agent.py
pulumi_aviatrix/aviatrix_controller_bgp_max_as_limit_config.py
pulumi_aviatrix/aviatrix_controller_cert_domain_config.py
pulumi_aviatrix/aviatrix_controller_config.py
pulumi_aviatrix/aviatrix_controller_email_config.py
pulumi_aviatrix/aviatrix_controller_email_exception_notification_config.py
pulumi_aviatrix/aviatrix_controller_gateway_keepalive_config.py
pulumi_aviatrix/aviatrix_controller_private_mode_config.py
pulumi_aviatrix/aviatrix_controller_private_oob.py
pulumi_aviatrix/aviatrix_controller_security_group_management_config.py
pulumi_aviatrix/aviatrix_copilot_association.py
pulumi_aviatrix/aviatrix_copilot_security_group_management_config.py
pulumi_aviatrix/aviatrix_datadog_agent.py
pulumi_aviatrix.egg-info/PKG-INFO
pulumi_aviatrix.egg-info/SOURCES.txt
pulumi_aviatrix.egg-info/dependency_links.txt
pulumi_aviatrix.egg-info/not-zip-safe
pulumi_aviatrix.egg-info/requires.txt
pulumi_aviatrix.egg-info/top_level.txt
