Metadata-Version: 2.1
Name: pulumi-aviatrix
Version: 0.0.10
Summary: A Pulumi package for creating and managing Aviatrix cloud resources.
Home-page: https://www.aviatrix.com
License: Apache-2.0
Project-URL: Repository, https://github.com/astipkovits/pulumi-aviatrix
Keywords: pulumi aviatrix category/cloud
Platform: UNKNOWN
